{
  "startdate": "20210722",
  "fullstartdate": "202107220700",
  "enddate": "20210723",
  "url": "/th?id=OHR.MinokakeRocks_EN-US9026307089_UHD.jpg&rf=LaDigue_UHD.jpg&pid=hp&w=1920&h=1080&rs=1&c=4",
  "urlbase": "/th?id=OHR.MinokakeRocks_EN-US9026307089",
  "copyright": "The Minokake-Iwa rocks off the coast of the Izu Peninsula, Japan (© Krzysztof Baranowski/Getty Images)",
  "copyrightlink": "https://www.bing.com/search?q=marine+day+japan&form=hpcapt&filters=HpDate%3a%2220210722_0700%22",
  "title": "Singing praises of the oceans",
  "quiz": "/search?q=Bing+homepage+quiz&filters=WQOskey:%22HPQuiz_20210722_MinokakeRocks%22&FORM=HPQUIZ",
  "wp": true,
  "hsh": "b0741f3baafc17bbefec1bcdafdc6b44",
  "drk": 1,
  "top": 1,
  "bot": 1,
  "hs": []
}
